gwinc/__init__.py
gwinc/__main__.py
gwinc/_version.py
gwinc/const.py
gwinc/gwinc_matlab.py
gwinc/io.py
gwinc/nb.py
gwinc/plot.py
gwinc/squeeze.py
gwinc/struct.py
gwinc/suspension.py
gwinc/trace.py
gwinc/__pycache__/struct.cpython-311.pyc
gwinc/ifo/__init__.py
gwinc/ifo/__main__.py
gwinc/ifo/noises.py
gwinc/ifo/Aplus/__init__.py
gwinc/ifo/Aplus/ifo.yaml
gwinc/ifo/CE1/__init__.py
gwinc/ifo/CE1/ifo.yaml
gwinc/ifo/CE2silica/__init__.py
gwinc/ifo/CE2silica/ifo.yaml
gwinc/ifo/CE2silicon/__init__.py
gwinc/ifo/CE2silicon/ifo.yaml
gwinc/ifo/Voyager/__init__.py
gwinc/ifo/Voyager/ifo.yaml
gwinc/ifo/aLIGO/__init__.py
gwinc/ifo/aLIGO/ifo.yaml
gwinc/noise/__init__.py
gwinc/noise/coatingthermal.py
gwinc/noise/newtonian.py
gwinc/noise/quantum.py
gwinc/noise/residualgas.py
gwinc/noise/seismic.py
gwinc/noise/substratethermal.py
gwinc/noise/suspensionthermal.py
gwinc/test/__init__.py
gwinc/test/__main__.py
gwinc/test/gen_cache.sh
gwinc-0.6.2.dist-info/LICENSE
gwinc-0.6.2.dist-info/METADATA
gwinc-0.6.2.dist-info/WHEEL
gwinc-0.6.2.dist-info/entry_points.txt
gwinc-0.6.2.dist-info/top_level.txt
gwinc-0.6.2.dist-info/RECORD
