Metadata-Version: 2.1
Name: gwinc
Version: 0.6.2
Summary: Gravitation Wave Interferometer Noise Calculator
Home-page: https://git.ligo.org/gwinc/pygwinc
Author: LIGO Scientific Collaboration
Author-email: jameson.rollins@ligo.org
License: UNLICENSE
Project-URL: Bug Tracker, https://git.ligo.org/gwinc/pygwinc/issues
Project-URL: Source Code, https://git.ligo.org/gwinc/pygwinc
Classifier: Development Status :: 4 - Beta
Classifier: Environment :: Console
Classifier: License :: OSI Approved :: The Unlicense (Unlicense)
Classifier: Topic :: Scientific/Engineering
Classifier: Topic :: Scientific/Engineering :: Astronomy
Classifier: Topic :: Scientific/Engineering :: Physics
Classifier: Intended Audience :: Science/Research
Classifier: Operating System :: OS Independent
Classifier: Programming Language :: Python
Classifier: Programming Language :: Python :: 3
Classifier: Programming Language :: Python :: 3.6
Classifier: Programming Language :: Python :: 3.7
Classifier: Programming Language :: Python :: 3.8
Requires-Python: >=3.6
License-File: LICENSE
Requires-Dist: h5py
Requires-Dist: ipython
Requires-Dist: matplotlib
Requires-Dist: numpy
Requires-Dist: pyyaml
Requires-Dist: scipy
Provides-Extra: range
Requires-Dist: inspiral-range; extra == "range"
